<?xml version="1.0" encoding="UTF-8"?>
<WeatherReport>
    <Report date="2025-09-04">
        <Location>
            <City>Ghaziabad</City>
            <State>Uttar Pradesh</State>
            <Country code="IN">India</Country>
        </Location>
        <Temperature>
            <High>38</High>
            <Low>27</Low>
        </Temperature>
    </Report>

    <Report date="2025-09-03">
        <Location>
            <City>Tokyo</City>
            <State>Tokyo Prefecture</State>
            <Country code="JP">Japan</Country>
        </Location>
        <Temperature>
            <High>31</High>
            <Low>22</Low>
        </Temperature>
    </Report>
</WeatherReport>